setup.py
gaepagseguro/__init__.py
gaepagseguro/admin_commands.py
gaepagseguro/connection_commands.py
gaepagseguro/model.py
gaepagseguro/pagseguro_facade.py
gaepagseguro/save_commands.py
gaepagseguro/search_commands.py
gaepagseguro/update_commands.py
gaepagseguro/validation_commands.py
gaepagseguro.egg-info/PKG-INFO
gaepagseguro.egg-info/SOURCES.txt
gaepagseguro.egg-info/dependency_links.txt
gaepagseguro.egg-info/not-zip-safe
gaepagseguro.egg-info/requires.txt
gaepagseguro.egg-info/top_level.txt
test/testloader.py