Metadata-Version: 1.1
Name: gaepagseguro
Version: 0.3
Summary: A client library for Google App Engine integration with pagseguro.com.br
Home-page: https://github.com/renzon/gaepagseguro
Author: Renzo Nuccitelli
Author-email: renzo.n@gmail.com
License: BSD
Platform: UNKNOWN
Classifier: Development Status :: 4 - Beta
Classifier: Environment :: Web Environment
Classifier: Intended Audience :: Developers
Classifier: License :: OSI Approved :: BSD License
Classifier: Operating System :: OS Independent
Classifier: Programming Language :: Python
Classifier: Framework :: Paste
